nbreproduce/__init__.py
nbreproduce/cli.py
nbreproduce/nbreproduce.py
nbreproduce-0.4.1.dist-info/AUTHORS.rst
nbreproduce-0.4.1.dist-info/LICENSE
nbreproduce-0.4.1.dist-info/METADATA
nbreproduce-0.4.1.dist-info/WHEEL
nbreproduce-0.4.1.dist-info/entry_points.txt
nbreproduce-0.4.1.dist-info/top_level.txt
nbreproduce-0.4.1.dist-info/RECORD
