Metadata-Version: 2.1
Name: nbreproduce
Version: 0.4.1
Summary: Reproduce Jupyter Notebooks inside Docker Containers.
Home-page: https://github.com/MridulS/nbreproduce
Author: Mridul Seth
Author-email: seth.mridul@gmail.com
License: BSD license
Keywords: nbreproduce
Platform: UNKNOWN
Classifier: Development Status :: 2 - Pre-Alpha
Classifier: Intended Audience :: Developers
Classifier: License :: OSI Approved :: BSD License
Classifier: Natural Language :: English
Classifier: Programming Language :: Python :: 3
Classifier: Programming Language :: Python :: 3.6
Classifier: Programming Language :: Python :: 3.7
Classifier: Programming Language :: Python :: 3.8
Requires-Python: >=3.6
Requires-Dist: nbformat
Requires-Dist: docker
